dozersim/__init__.py
dozersim/components/__init__.py
dozersim/components/ballbearing.py
dozersim/components/ballscrew.py
dozersim/components/battery.py
dozersim/components/electricmotor.py
dozersim/components/flywheel.py
dozersim/components/gearbox.py
dozersim/components/inertia.py
dozersim/components/linkage.py
dozersim/components/materials.py
dozersim/components/multiplier.py
dozersim/components/servodrive.py
dozersim/components/spring.py
dozersim/components/suspension.py
dozersim/components/tools.py
dozersim/components/transformer.py
dozersim/constraints/__init__.py
dozersim/constraints/_constraints.py
dozersim/data/gait_data.json
dozersim/data/sit2stand_data.json
dozersim/data/supplier_data.db
dozersim/modelling/__init__.py
dozersim/modelling/_model.py
dozersim/modelling/_settings.py
dozersim/objectives/__init__.py
dozersim/objectives/_objectives.py
dozersim/parameters/__init__.py
dozersim/parameters/_parameters.py
dozersim/path/__init__.py
dozersim/path/_path.py
dozersim/recipes/__init__.py
dozersim/recipes/actuators.py
dozersim/results/__init__.py
dozersim/results/_results.py
dozersim/simulation/__init__.py
dozersim/simulation/_simulation.py
dozersim/sources/__init__.py
dozersim/sources/constant.py
dozersim/sources/gaitdata.py
dozersim/sources/gaussian.py
dozersim/sources/gaussiansfilter.py
dozersim/sources/sit2stand.py
dozersim/sources/timesource.py
dozersim/sources/trapeziod.py
dozersim/suppliers/__init__.py
dozersim/suppliers/_link.py
dozersim/suppliers/_suppliers.py
dozersim/utils/__init__.py
dozersim/utils/_utils.py
dozersim/variables/__init__.py
dozersim/variables/_variables.py
dozersim/visualizations/__init__.py
dozersim/visualizations/_plotting.py
dozersim/visualizations/_visualization.py
dozersim-0.2.9.dist-info/LICENSE
dozersim-0.2.9.dist-info/METADATA
dozersim-0.2.9.dist-info/WHEEL
dozersim-0.2.9.dist-info/RECORD
