Metadata-Version: 2.3
Name: dozersim
Version: 0.2.9
Summary: Simulation and optmization framework for drives
Author: Cor Meijneke
Author-email: c.meijneke@tudelft.nl
Requires-Python: >=3.12,<4.0
Classifier: Programming Language :: Python :: 3
Classifier: Programming Language :: Python :: 3.12
Classifier: Programming Language :: Python :: 3.13
Requires-Dist: Pint (>=0.24.4,<0.25.0)
Requires-Dist: PyQt6 (>=6.7.1,<7.0.0)
Requires-Dist: SQLAlchemy (>=2.0.23,<3.0.0)
Requires-Dist: matplotlib (>=3.8.2,<4.0.0)
Requires-Dist: numpy (>=2.3.1,<3.0.0)
Requires-Dist: pandas (>=2.1.3,<3.0.0)
Requires-Dist: prettytable (>=3.9.0,<4.0.0)
Requires-Dist: scipy (>=1.16.0,<2.0.0)
Requires-Dist: sympy (>=1.14.0,<2.0.0)
